{
    "name": "2D Plotter Explorations",
    "id": "2d-plotter-explorations",
    "description": "Various explorations into designing a 2D plotter including repurposing a 3D printer, and engineering a 2D plotter from scratch.",
    "end_date": "2020-07-29",
    "images": [
        {
            "name": "Pen holder attached to 3d Printer",
            "src": "2d-plotter-explorations/1.jpg"
        },
        {
            "name": "All prototypes",
            "src": "2d-plotter-explorations/2.jpg"
        },
        {
            "name": "Successful print",
            "src": "2d-plotter-explorations/3.jpg"
        },
        {
            "name": "Playing around with circuits",
            "src": "2d-plotter-explorations/4.jpg"
        },
        {
            "name": "Parts ready for print",
            "src": "2d-plotter-explorations/5.jpg"
        },
        {
            "name": "The last assembly",
            "src": "2d-plotter-explorations/6.jpg"
        }
    ],
    "links": [
        {
            "name": "GitHub Repository",
            "src": "https://github.com/TravisBumgarner/Plotter-Explorations"
        },
        {
            "name": "YouTube Playlist - 3D Printer to 2D Plotter",
            "src": "https://www.youtube.com/watch?v=eNIFybCENtE&list=PL58d_qyxyaOF-66-4kabZ9wtJEJlURT8i"
        },
        {
            "name": "YouTube Playlist - 2D Plotter From Scratch",
            "src": "https://www.youtube.com/watch?v=lJApWtDMxLM&list=PL58d_qyxyaOGu1aUYKD9BjNBRsrKP4v3W"
        }
    ],
    "preview_img": {
        "name": "2D Plotter result",
        "src": "2d-plotter-explorations/thumbnail.jpg"
    }
}